README.md
setup.py
ollama_assistant/__init__.py
ollama_assistant/assistant.py
ollama_assistant/assistant_thread.py
ollama_assistant/chat.py
ollama_assistant/client.py
ollama_assistant/main.py
ollama_assistant/messages.py
ollama_assistant/models.py
ollama_assistant/services.py
ollama_assistant/settings.py
ollama_assistant/utils.py
ollama_assistant.egg-info/PKG-INFO
ollama_assistant.egg-info/SOURCES.txt
ollama_assistant.egg-info/dependency_links.txt
ollama_assistant.egg-info/requires.txt
ollama_assistant.egg-info/top_level.txt